cpan115/Auth.py
cpan115/Downloader.py
cpan115/File.py
cpan115/Rb.py
cpan115/Uploader.py
cpan115/User.py
cpan115/__init__.py
cpan115/authtype/Jwt.py
cpan115/authtype/OAuth.py
cpan115/authtype/__init__.py
cpan115/cli.py
cpan115/model/Base.py
cpan115/model/model.py
cpan115/utils/Constants.py
cpan115/utils/EnvConfig.py
cpan115/utils/Logger.py
cpan115/utils/__init__.py
cpan115/utils/md5.py
cpan115/utils/sha.py
cpan115-0.1.0.dist-info/WHEEL
cpan115-0.1.0.dist-info/entry_points.txt
cpan115-0.1.0.dist-info/METADATA
cpan115-0.1.0.dist-info/RECORD
