Metadata-Version: 2.3
Name: cpan115
Version: 0.1.0
Summary: 115云盘的python接口文档(非官方)
Author: zoushucai
Author-email: zoushucai <zoushucai@users.noreply.github.com>
Requires-Dist: alibabacloud-oss-v2>=1.2.0
Requires-Dist: click>=8.3.0
Requires-Dist: dotenv>=0.9.9
Requires-Dist: httpx[http2]>=0.28.1
Requires-Dist: loguru>=0.7.3
Requires-Dist: pydantic>=2.12.3
Requires-Dist: requests>=2.32.5
Requires-Dist: tenacity>=9.1.2
Requires-Dist: tqdm>=4.66.0
Requires-Python: >=3.10
Project-URL: Changelog, https://github.com/zoushucai/cpan115/blob/main/CHANGELOG.md
Project-URL: Documentation, https://cpan115.readthedocs.org
Project-URL: Homepage, https://github.com/zoushucai/cpan115
Project-URL: Issues, https://github.com/zoushucai/cpan115/issues
Project-URL: Repository, https://github.com/zoushucai/cpan115.git
